{
  "id": "2412.16110",
  "title": "Performance limits of spectro-temporal unitary transformations for\n  coherent modulation",
  "authors": "Callum Deakin, Xi Chen",
  "authorsParsed": [
    [
      "Deakin",
      "Callum",
      ""
    ],
    [
      "Chen",
      "Xi",
      ""
    ]
  ],
  "versions": [
    {
      "version": "v1",
      "created": "Fri, 20 Dec 2024 17:49:40 GMT"
    }
  ],
  "updateDate": "2024-12-23",
  "timestamp": 1734716980000,
  "abstract": "  We analyse the performance limits of coherent modulation based on lossless\nunitary transformations, demonstrating that they can achieve high ($>$30~dB)\nSINAD and outperform conventional IQ modulators at equivalent transmitter laser\npowers.\n",
  "subjects": [
    "Electrical Engineering and Systems Science/Signal Processing",
    "Physics/Optics"
  ],
  "license": "http://creativecommons.org/licenses/by/4.0/",
  "blobId": "L4BK9X_ZwZKX37E-RsNUQd71-aQGxBtXdkQ9jUf9tW0",
  "pdfSize": "295598"
}