{"id":"2407.20327","title":"Extreme Ionizing Properties of Metal-Poor, Muv ~ -12 Star Complex in the\n  first Gyr","authors":"E. Vanzella, F. Loiacono, M. Messa, M. Castellano, P. Bergamini, A.\n  Zanella, F. Annibali, B. Sun, M. Dickinson, A. Adamo, F. Calura, M. Ricotti,\n  P. Rosati, M. Meneghetti, C. Grillo, M. Bradac, C. J. Conselice, H. Yan, A.\n  Bolamperti, U. Mestric, R. Gilli, M. Gronke, C. Willott, E. Sani, A. Acebron,\n  A. Comastri, M. Mignoli, C. Gruppioni, A. Mercurio, V. Strait, R. Pascale, M.\n  Annunziatella, B. L. Frye, L. D. Bradley, N. A. Grogin, A. M. Koekemoer, S.\n  Ravindranath, J. C. J. D'Silva, J. Summers, G. Rihtar and R. Windhorst","authorsParsed":[["Vanzella","E.",""],["Loiacono","F.",""],["Messa","M.",""],["Castellano","M.",""],["Bergamini","P.",""],["Zanella","A.",""],["Annibali","F.",""],["Sun","B.",""],["Dickinson","M.",""],["Adamo","A.",""],["Calura","F.",""],["Ricotti","M.",""],["Rosati","P.",""],["Meneghetti","M.",""],["Grillo","C.",""],["Bradac","M.",""],["Conselice","C. J.",""],["Yan","H.",""],["Bolamperti","A.",""],["Mestric","U.",""],["Gilli","R.",""],["Gronke","M.",""],["Willott","C.",""],["Sani","E.",""],["Acebron","A.",""],["Comastri","A.",""],["Mignoli","M.",""],["Gruppioni","C.",""],["Mercurio","A.",""],["Strait","V.",""],["Pascale","R.",""],["Annunziatella","M.",""],["Frye","B. L.",""],["Bradley","L. D.",""],["Grogin","N. A.",""],["Koekemoer","A. M.",""],["Ravindranath","S.",""],["D'Silva","J. C. J.",""],["Summers","J.",""],["Rihtar","G.",""],["Windhorst","R.",""]],"versions":[{"version":"v1","created":"Mon, 29 Jul 2024 18:00:01 GMT"}],"updateDate":"2024-07-31","timestamp":1722276001000,"abstract":"  We report the serendipitous discovery of a faint (M_UV > -12.2),\nlow-metallicity (Z ~ 0.02 Zsun), ionizing source (dubbed T2c) with a\nspectroscopic redshift of z=6.146. T2c is part of a larger structure amplified\nby the Hubble Frontier Field galaxy cluster MACSJ0416, and was observed with\nJWST/NIRSpec IFU. Stacking the short-wavelength NIRCam data reveals no stellar\ncontinuum detection down to a magnitude limit of m_UV ~ 31.0 (3 sigma).\nHowever, prominent Hb, [OIII]4959,5007, and Ha emissions are detected, with\nequivalent widths exceeding 200A, 800A, and 1300A (3 sigma), respectively. The\ncorresponding intrinsic (magnification-corrected x23 +/- 3) ultraviolet and\noptical rest-frame magnitudes exceed 34.4 and 33.9 (corresponding to M_uv and\nM_opt fainter than -12.2 and -12.8, at lambda_rest ~ 2000A and ~5000A,\nrespectively), suggesting a stellar mass lower than a few 10^4 Msun under an\ninstantaneous burst scenario. The inferred ionizing photon production\nefficiency (xi_ion) is high, xi_ion >~ 26.08(25.86) 3(5)sigma, assuming no dust\nattenuation and no Lyman continuum leakage, indicating the presence of massive\nstars despite the low mass of the object. The very poor sampling of the initial\nmass function at such low mass star-forming complex suggests that the formation\nof very massive stars might be favored in very low metallicity environments.\nT2c is surrounded by Balmer and weak oxygen emission on a spatial scale of a\nfew hundred parsecs after correcting for lensing effects. This system resembles\nan HII region potentially powered by currently undetected, extremely efficient,\nlow-metallicity star complexes or clusters. We propose that massive O-type\nstars populate this low-mass and metallicity high-redshift satellites, likely\ncaught in an early and short formation phase, contributing to the ionization of\nthe surrounding medium.\n","subjects":["Astrophysics/Astrophysics of Galaxies"],"license":"http://arxiv.org/licenses/nonexclusive-distrib/1.0/"}