{"id":"2407.16259","title":"Fourier restriction for Schatten class operators and functions on phase\n  space","authors":"Franz Luef, Helge J{\\o}rgen Samuelsen","authorsParsed":[["Luef","Franz",""],["Samuelsen","Helge Jørgen",""]],"versions":[{"version":"v1","created":"Tue, 23 Jul 2024 07:55:31 GMT"},{"version":"v2","created":"Sun, 28 Jul 2024 12:16:35 GMT"}],"updateDate":"2024-07-30","timestamp":1721721331000,"abstract":"  We formulate a variant of Fourier restriction for operators in Schatten\nclasses, where the Fourier-Wigner transform of a bounded operator replaces the\nFourier transform of a function. The Fourier-Wigner transform is closely\nrelated to the group Fourier transform of the Heisenberg group. The first\nresult shows that Fourier-Wigner restriction for Schatten class operators is\nequivalent to the restriction of the symplectic Fourier transform of functions\non phase space. We deduce various Schatten class results for the quantum\nFourier extension operator and answer a conjecture by Mishra and Vemuri\nconcerning the Weyl transform of measures in the affirmative.\n","subjects":["Mathematics/Functional Analysis","Mathematics/Classical Analysis and ODEs"],"license":"http://arxiv.org/licenses/nonexclusive-distrib/1.0/"}